reader/__init__.py
reader/__main__.py
reader/config.cfg
reader/feed.py
reader/viewer.py
mytest_pythonreader2-1.0.82.dist-info/LICENSE
mytest_pythonreader2-1.0.82.dist-info/METADATA
mytest_pythonreader2-1.0.82.dist-info/WHEEL
mytest_pythonreader2-1.0.82.dist-info/entry_points.txt
mytest_pythonreader2-1.0.82.dist-info/top_level.txt
mytest_pythonreader2-1.0.82.dist-info/RECORD
