Metadata-Version: 2.1
Name: mytest-pythonreader2
Version: 1.0.82
Summary: Read the latest Real Python tutorials
Home-page: https://github.com/realpython/reader
Author: Real Python
Author-email: info@realpython.com
License: MIT
Platform: UNKNOWN
Classifier: License :: OSI Approved :: MIT License
Classifier: Programming Language :: Python
Classifier: Programming Language :: Python :: 3
License-File: LICENSE
Requires-Dist: feedparser
Requires-Dist: html2text
